LICENSE
MANIFEST.in
README.rst
setup.py
django_subcommander/__init__.py
django_subcommander.egg-info/PKG-INFO
django_subcommander.egg-info/SOURCES.txt
django_subcommander.egg-info/dependency_links.txt
django_subcommander.egg-info/top_level.txt