Metadata-Version: 1.0
Name: django-subcommander
Version: 0.1
Summary: Write Django management commands that have subcommands.
Home-page: https://github.com/votizen/django-subcommander
Author: Erik Rose
Author-email: erikrose@grinchcentral.com
License: MIT
Keywords: django,subcommand,command,nested,management
Platform: UNKNOWN
Classifier: Development Status :: 4 - Beta
Classifier: Environment :: Web Environment
Classifier: Framework :: Django
Classifier: Intended Audience :: Developers
Classifier: Natural Language :: English
Classifier: License :: OSI Approved :: MIT License
Classifier: Programming Language :: Python :: 2
Classifier: Programming Language :: Python :: 2.6
Classifier: Programming Language :: Python :: 2.7
Classifier: Topic :: Software Development :: Libraries
